AUTHORS
LICENSE
MANIFEST.in
README.md
setup.cfg
setup.py
versioneer.py
ipsframework/__init__.py
ipsframework/_version.py
ipsframework/cca_es_spec.py
ipsframework/component.py
ipsframework/componentRegistry.py
ipsframework/configurationManager.py
ipsframework/convert_log_function.py
ipsframework/dakota_bridge.py
ipsframework/dataManager.py
ipsframework/debug.py
ipsframework/eventService.py
ipsframework/eventServiceProxy.py
ipsframework/ips.py
ipsframework/ipsExceptions.py
ipsframework/ipsLogging.py
ipsframework/ips_dakota_client.py
ipsframework/ips_dakota_dynamic.py
ipsframework/ips_es_spec.py
ipsframework/ipsutil.py
ipsframework/messages.py
ipsframework/node_structure.py
ipsframework/platformspec.py
ipsframework/portalBridge.py
ipsframework/resourceHelper.py
ipsframework/resourceManager.py
ipsframework/runspaceInitComponent.py
ipsframework/services.py
ipsframework/taskManager.py
ipsframework/topicManager.py
ipsframework.egg-info/PKG-INFO
ipsframework.egg-info/SOURCES.txt
ipsframework.egg-info/dependency_links.txt
ipsframework.egg-info/entry_points.txt
ipsframework.egg-info/requires.txt
ipsframework.egg-info/top_level.txt
ipsframework.egg-info/zip-safe
ipsframework/utils/HTML.py
ipsframework/utils/__init__.py