Metadata-Version: 2.1
Name: ipsframework
Version: 0.8.0
Summary: Integrated Plasma Simulator (IPS) Framework
Home-page: https://ips-framework.readthedocs.io
License: BSD
Project-URL: Documentation, https://ips-framework.readthedocs.io
Project-URL: Source, https://github.com/HPC-SimTools/IPS-framework
Project-URL: Tracker, https://github.com/HPC-SimTools/IPS-framework/issues
Classifier: Programming Language :: Python :: 3
Classifier: Programming Language :: Python :: 3.6
Classifier: Programming Language :: Python :: 3.7
Classifier: Programming Language :: Python :: 3.8
Classifier: Programming Language :: Python :: 3.9
Classifier: Programming Language :: Python :: 3.10
Classifier: License :: OSI Approved :: BSD License
Classifier: Operating System :: MacOS :: MacOS X
Classifier: Operating System :: POSIX :: Linux
Requires-Python: >=3.6
License-File: LICENSE
License-File: AUTHORS
